pipeline_name/__about__.py
pipeline_name/__init__.py
pipeline_name/__main__.py
pipeline_name/config.yaml
pipeline_name/cli/__init__.py
pipeline_name/workflow/Snakefile
pipeline_name-0.0.2.dist-info/METADATA
pipeline_name-0.0.2.dist-info/WHEEL
pipeline_name-0.0.2.dist-info/entry_points.txt
pipeline_name-0.0.2.dist-info/licenses/LICENSE.txt
pipeline_name-0.0.2.dist-info/RECORD
