Metadata-Version: 2.1
Name: pipeline-name
Version: 0.0.2
Project-URL: Documentation, https://github.com/Wytamma/snk-pipeline-package-example#readme
Project-URL: Issues, https://github.com/Wytamma/snk-pipeline-package-example/issues
Project-URL: Source, https://github.com/Wytamma/snk-pipeline-package-example
Author-email: Wytamma Wirth <wytamma.wirth@me.com>
License-Expression: MIT
License-File: LICENSE.txt
Classifier: Development Status :: 4 - Beta
Classifier: Programming Language :: Python
Classifier: Programming Language :: Python :: 3.7
Classifier: Programming Language :: Python :: 3.8
Classifier: Programming Language :: Python :: 3.9
Classifier: Programming Language :: Python :: 3.10
Classifier: Programming Language :: Python :: 3.11
Classifier: Programming Language :: Python :: Implementation :: CPython
Classifier: Programming Language :: Python :: Implementation :: PyPy
Requires-Python: >=3.7
Requires-Dist: snk
